LICENSE.txt
MANIFEST.in
README.md
setup.cfg
setup.py
wordster/__init__.py
wordster/wordster.py
wordster.egg-info/PKG-INFO
wordster.egg-info/SOURCES.txt
wordster.egg-info/dependency_links.txt
wordster.egg-info/requires.txt
wordster.egg-info/top_level.txt