Metadata-Version: 1.1
Name: wordster
Version: 0.0.2
Summary: A small wrapper around official Merriam Webster dictionary
Home-page: https://github.com/rahulxxarora/wordster
Author: Rahul Arora
Author-email: coderahul94@gmail.com
License: MIT
Keywords: dictionary merriam webster meaning
Platform: UNKNOWN
Classifier: Intended Audience :: Developers
Classifier: License :: OSI Approved :: MIT License
Classifier: Programming Language :: Python
Classifier: Operating System :: POSIX
